Metadata-Version: 1.1
Name: formatter
Version: 1.0.2
Summary: A Python source formatter that uses the tokenize library
Home-page: https://github.com/WoLpH/formatter
Author: Rick van Hattem
Author-email: Wolph@wol.ph
License: BSD
Platform: UNKNOWN
Classifier: License :: OSI Approved :: BSD License
